microsoft_authentication/__init__.py
microsoft_authentication/admin.py
microsoft_authentication/apps.py
microsoft_authentication/models.py
microsoft_authentication/tests.py
microsoft_authentication/urls.py
microsoft_authentication/views.py
microsoft_authentication/auth/__init__.py
microsoft_authentication/auth/auth_decorators.py
microsoft_authentication/auth/auth_utils.py
microsoft_authentication/migrations/__init__.py
django_microsoft_auth_sync-0.1.8.dist-info/LICENSE
django_microsoft_auth_sync-0.1.8.dist-info/METADATA
django_microsoft_auth_sync-0.1.8.dist-info/WHEEL
django_microsoft_auth_sync-0.1.8.dist-info/top_level.txt
django_microsoft_auth_sync-0.1.8.dist-info/RECORD
